<?xml version="1.0" encoding="UTF-8"?><vehicle data_version="3" bodies_id="8"><editor_placement_offset y="-4.061793"/><authors/><bodies><body unique_id="3"><components><c><o r="-1,0,0,0,-1,0,0,0,1" bc="454545" ac="454545" sc="6,454545,454545,6E6E6E,6E6E6E,6E6E6E,6E6E6E"><vp y="-1" z="-3"/></o></c><c><o r="0,0,-1,1,0,0,0,-1,0" bc="454545" ac="454545" sc="6,6E6E6E,6E6E6E,454545,6E6E6E,6E6E6E,6E6E6E"><vp x="1" y="-1" z="-2"/></o></c><c><o r="0,0,-1,1,0,0,0,-1,0" bc="454545" ac="454545" sc="6,6E6E6E,6E6E6E,454545,454545,6E6E6E,6E6E6E"><vp x="2" y="-1" z="-2"/></o></c><c><o r="0,0,-1,1,0,0,0,-1,0" bc="454545" ac="454545" sc="6,6E6E6E,6E6E6E,6E6E6E,6E6E6E,6E6E6E,6E6E6E"><vp x="3" y="-1" z="-2"/></o></c><c t="2"><o r="0,0,-1,1,0,0,0,-1,0" bc="454545" ac="454545" sc="6,6E6E6E,886247,454545,454545,6E6E6E,6E6E6E"><vp x="-1" y="-1" z="-2"/></o></c><c t="2"><o r="0,0,-1,1,0,0,0,-1,0" bc="454545" ac="454545" sc="6,6E6E6E,886247,454545,454545,6E6E6E,6E6E6E"><vp x="-2" y="-1" z="-2"/></o></c><c t="2"><o r="0,0,-1,1,0,0,0,-1,0" bc="454545" ac="454545" sc="6,6E6E6E,886247,886247,6E6E6E,6E6E6E,6E6E6E"><vp x="-3" y="-1" z="-2"/></o></c><c><o r="1,0,0,0,0,-1,0,1,0" bc="454545" ac="454545" sc="6,886247,6E6E6E,454545,454545,886247,6E6E6E"><vp x="-3" y="-1" z="-3"/></o></c><c><o r="1,0,0,0,0,-1,0,1,0" bc="454545" ac="454545" sc="6,6E6E6E,6E6E6E,454545,6E6E6E,886247,6E6E6E"><vp x="-3" y="-1" z="-4"/></o></c><c><o r="1,0,0,0,0,-1,0,1,0" bc="454545" ac="454545" sc="6,6E6E6E,6E6E6E,454545,454545,6E6E6E,6E6E6E"><vp x="-3" y="-1" z="-5"/></o></c><c><o r="1,0,0,0,0,-1,0,1,0" bc="454545" ac="454545" sc="6,6E6E6E,6E6E6E,454545,454545,886247,6E6E6E"><vp x="-3" y="-1" z="-6"/></o></c><c><o r="1,0,0,0,0,-1,0,1,0" bc="454545" ac="454545" sc="6,886247,6E6E6E,6E6E6E,454545,886247,6E6E6E"><vp x="-3" y="-1" z="-7"/></o></c><c><o r="1,0,0,0,0,-1,0,1,0" bc="454545" ac="454545" sc="6,886247,6E6E6E,454545,454545,7E4422,6E6E6E"><vp x="-3" y="-1" z="-8"/></o></c><c><o r="1,0,0,0,0,-1,0,1,0" bc="454545" ac="454545" sc="6,886247,6E6E6E,6E6E6E,6E6E6E,7E4422,6E6E6E"><vp x="-3" y="-1" z="-9"/></o></c><c t="1"><o r="1,0,0,0,0,-1,0,1,0" bc="454545" ac="454545" sc="6,6E6E6E,6E6E6E,454545,454545,886247,6E6E6E"><vp x="3" y="-1" z="-3"/></o></c><c t="1"><o r="1,0,0,0,0,-1,0,1,0" bc="454545" ac="454545" sc="6,886247,6E6E6E,454545,6E6E6E,886247,6E6E6E"><vp x="3" y="-1" z="-4"/></o></c><c t="1"><o r="1,0,0,0,0,-1,0,1,0" bc="454545" ac="454545" sc="6,6E6E6E,6E6E6E,454545,454545,886247,6E6E6E"><vp x="3" y="-1" z="-5"/></o></c><c t="1"><o r="1,0,0,0,0,-1,0,1,0" bc="454545" ac="454545" sc="6,6E6E6E,6E6E6E,454545,454545,6E6E6E,6E6E6E"><vp x="3" y="-1" z="-6"/></o></c><c t="1"><o r="1,0,0,0,0,-1,0,1,0" bc="454545" ac="454545" sc="6,6E6E6E,6E6E6E,6E6E6E,454545,6E6E6E,6E6E6E"><vp x="3" y="-1" z="-7"/></o></c><c t="1"><o r="1,0,0,0,0,-1,0,1,0" bc="454545" ac="454545" sc="6,6E6E6E,6E6E6E,454545,454545,6E6E6E,6E6E6E"><vp x="3" y="-1" z="-8"/></o></c><c t="1"><o r="1,0,0,0,0,-1,0,1,0" bc="454545" ac="454545" sc="6,6E6E6E,6E6E6E,6E6E6E,6E6E6E,6E6E6E,6E6E6E"><vp x="3" y="-1" z="-9"/></o></c><c><o bc="454545" ac="454545" sc="6,6E6E6E,6E6E6E,454545,454545,6E6E6E,6E6E6E"><vp x="-2" y="-1" z="-9"/></o></c><c><o bc="454545" ac="454545" sc="6,6E6E6E,6E6E6E,454545,454545,6E6E6E,6E6E6E"><vp x="-1" y="-1" z="-9"/></o></c><c><o bc="454545" ac="454545" sc="6,6E6E6E,6E6E6E,454545,454545,6E6E6E,6E6E6E"><vp y="-1" z="-9"/></o></c><c><o bc="454545" ac="454545" sc="6,6E6E6E,6E6E6E,454545,454545,6E6E6E,6E6E6E"><vp x="1" y="-1" z="-9"/></o></c><c><o bc="454545" ac="454545" sc="6,6E6E6E,6E6E6E,454545,454545,6E6E6E,6E6E6E"><vp x="2" y="-1" z="-9"/></o></c><c><o r="0,0,-1,1,0,0,0,-1,0" bc="454545" ac="454545" sc="6,6E6E6E,6E6E6E,454545,454545,6E6E6E,454545"><vp x="-2" y="-1" z="-4"/></o></c><c><o r="0,0,-1,1,0,0,0,-1,0" bc="454545" ac="454545" sc="6,6E6E6E,6E6E6E,454545,454545,6E6E6E,454545"><vp x="-1" y="-1" z="-4"/></o></c><c><o r="0,0,-1,1,0,0,0,-1,0" bc="454545" ac="454545" sc="6,6E6E6E,6E6E6E,6E6E6E,6E6E6E,6E6E6E,454545"><vp y="-1" z="-4"/></o></c><c><o r="0,0,-1,1,0,0,0,-1,0" bc="454545" ac="454545" sc="6,6E6E6E,6E6E6E,454545,454545,6E6E6E,454545"><vp x="1" y="-1" z="-4"/></o></c><c><o r="0,0,-1,1,0,0,0,-1,0" bc="454545" ac="454545" sc="6,6E6E6E,6E6E6E,454545,454545,6E6E6E,454545"><vp x="2" y="-1" z="-4"/></o></c><c><o r="0,0,-1,1,0,0,0,-1,0" bc="454545" ac="454545" sc="6,6E6E6E,6E6E6E,454545,454545,454545,6E6E6E"><vp x="-2" y="-1" z="-7"/></o></c><c><o r="0,0,-1,1,0,0,0,-1,0" bc="454545" ac="454545" sc="6,6E6E6E,6E6E6E,454545,454545,454545,6E6E6E"><vp x="-1" y="-1" z="-7"/></o></c><c><o r="0,0,-1,1,0,0,0,-1,0" bc="454545" ac="454545" sc="6,6E6E6E,6E6E6E,6E6E6E,6E6E6E,454545,6E6E6E"><vp y="-1" z="-7"/></o></c><c><o r="0,0,-1,1,0,0,0,-1,0" bc="454545" ac="454545" sc="6,6E6E6E,6E6E6E,454545,454545,454545,6E6E6E"><vp x="2" y="-1" z="-7"/></o></c><c><o bc="454545" ac="454545" sc="6,6E6E6E,6E6E6E,454545,454545,454545,454545"><vp x="-2" y="-1" z="-6"/></o></c><c><o bc="454545" ac="454545" sc="6,6E6E6E,6E6E6E,454545,454545,454545,454545"><vp x="-2" y="-1" z="-5"/></o></c><c><o bc="454545" ac="454545" sc="6,6E6E6E,6E6E6E,454545,454545,454545,454545"><vp x="-1" y="-1" z="-6"/></o></c><c><o bc="454545" ac="454545" sc="6,6E6E6E,6E6E6E,454545,454545,454545,454545"><vp x="-1" y="-1" z="-5"/></o></c><c><o bc="454545" ac="454545" sc="6,6E6E6E,6E6E6E,6E6E6E,6E6E6E,454545,454545"><vp y="-1" z="-6"/></o></c><c><o bc="454545" ac="454545" sc="6,6E6E6E,6E6E6E,6E6E6E,6E6E6E,454545,454545"><vp y="-1" z="-5"/></o></c><c><o bc="454545" ac="454545" sc="6,6E6E6E,6E6E6E,454545,454545,454545,454545"><vp x="1" y="-1" z="-6"/></o></c><c><o bc="454545" ac="454545" sc="6,6E6E6E,6E6E6E,454545,454545,454545,454545"><vp x="1" y="-1" z="-5"/></o></c><c><o bc="454545" ac="454545" sc="6,6E6E6E,6E6E6E,454545,454545,454545,454545"><vp x="2" y="-1" z="-6"/></o></c><c><o bc="454545" ac="454545" sc="6,6E6E6E,6E6E6E,454545,454545,454545,454545"><vp x="2" y="-1" z="-5"/></o></c><c d="linear_compact_module"><o r="1,0,0,0,0,1,0,-1,0" bc="6E6E6E" bc2="454545" bc3="454545" ac="454545" sc="5,6E6E6E,454545,454545,454545,454545"><vp y="1" z="-2"/></o></c><c d="linear_compact_module"><o r="1,0,0,0,0,1,0,-1,0" bc="6E6E6E" bc2="454545" bc3="454545" ac="454545" sc="5,6E6E6E,454545,454545,454545,454545"><vp y="4" z="-2"/></o></c><c d="linear_compact_module"><o r="1,0,0,0,0,1,0,-1,0" bc="6E6E6E" bc2="454545" bc3="454545" ac="454545" sc="5,6E6E6E,454545,454545,454545,454545"><vp y="5" z="-2"/></o></c><c d="linear_compact_module"><o r="1,0,0,0,0,1,0,-1,0" bc="6E6E6E" bc2="454545" bc3="454545" ac="454545" sc="5,6E6E6E,454545,454545,454545,454545"><vp y="6" z="-2"/></o></c><c d="linear_compact_module"><o r="1,0,0,0,0,1,0,-1,0" bc="6E6E6E" bc2="454545" bc3="454545" ac="454545" sc="5,6E6E6E,454545,454545,454545,454545"><vp y="7" z="-2"/></o></c><c d="linear_compact_module"><o r="1,0,0,0,0,1,0,-1,0" bc="6E6E6E" bc2="454545" bc3="454545" ac="454545" sc="5,6E6E6E,454545,454545,454545,454545"><vp y="8" z="-2"/></o></c><c d="battery_medium"><o r="1,0,0,0,1,0,0,0,1" bc="454545" ac="454545" sc="6" spawn_charge="0"><vp x="2" z="-6"/><logic_slots><slot/><slot/><slot/></logic_slots></o></c><c d="linear_compact_module"><o r="1,0,0,0,0,1,0,-1,0" bc="454545" ac="454545" sc="5,6E6E6E,6E6E6E,6E6E6E,6E6E6E,6E6E6E"><vp y="-1" z="-2"/></o></c><c><o r="1,0,0,0,0,1,0,-1,0" bc="454545" ac="454545" sc="6,6E6E6E,886247,454545,454545,7E4422,6E6E6E"><vp x="-3" y="-1" z="-1"/></o></c><c><o r="1,0,0,0,0,1,0,-1,0" bc="454545" ac="454545" sc="6,6E6E6E,7E4422,454545,454545,7E4422,6E6E6E"><vp x="-3" y="-1"/></o></c><c><o r="1,0,0,0,0,1,0,-1,0" bc="454545" ac="454545" sc="6,6E6E6E,7E4422,454545,454545,7E4422,6E6E6E"><vp x="-3" y="-1" z="1"/></o></c><c><o r="1,0,0,0,0,1,0,-1,0" bc="454545" ac="454545" sc="6,6E6E6E,886247,454545,454545,7E4422,6E6E6E"><vp x="-3" y="-1" z="2"/></o></c><c><o r="1,0,0,0,0,1,0,-1,0" bc="454545" ac="454545" sc="6,6E6E6E,886247,454545,454545,886247,6E6E6E"><vp x="-3" y="-1" z="3"/></o></c><c><o r="1,0,0,0,0,1,0,-1,0" bc="454545" ac="454545" sc="6,6E6E6E,886247,454545,454545,886247,6E6E6E"><vp x="-3" y="-1" z="4"/></o></c><c><o r="-1,0,0,0,-1,0,0,0,1" bc="454545" ac="454545" sc="6,6E6E6E,886247,6E6E6E,454545,6E6E6E,886247"><vp x="-3" y="-2" z="5"/></o></c><c d="02_wedge"><o r="1,0,0,0,0,1,0,-1,0" bc="454545" ac="454545" sc="5,886247,6E6E6E,6E6E6E,454545,886247"><vp x="-3" y="-1" z="5"/></o></c><c><o r="-1,0,0,0,-1,0,0,0,1" bc="454545" ac="454545" sc="6,454545,454545,6E6E6E,6E6E6E,6E6E6E,6E6E6E"><vp x="3" y="-1" z="-1"/></o></c><c><o r="-1,0,0,0,-1,0,0,0,1" bc="454545" ac="454545" sc="6,454545,454545,6E6E6E,6E6E6E,6E6E6E,6E6E6E"><vp x="3" y="-1"/></o></c><c><o r="-1,0,0,0,-1,0,0,0,1" bc="454545" ac="454545" sc="6,454545,454545,6E6E6E,6E6E6E,6E6E6E,6E6E6E"><vp x="3" y="-1" z="1"/></o></c><c><o r="-1,0,0,0,-1,0,0,0,1" bc="454545" ac="454545" sc="6,454545,454545,6E6E6E,6E6E6E,886247,6E6E6E"><vp x="3" y="-1" z="2"/></o></c><c><o r="-1,0,0,0,-1,0,0,0,1" bc="454545" ac="454545" sc="6,454545,454545,6E6E6E,886247,886247,6E6E6E"><vp x="3" y="-1" z="3"/></o></c><c><o r="-1,0,0,0,-1,0,0,0,1" bc="454545" ac="454545" sc="6,454545,454545,6E6E6E,886247,886247,886247"><vp x="3" y="-1" z="4"/></o></c><c d="02_wedge"><o r="1,0,0,0,0,1,0,-1,0" bc="454545" ac="454545" sc="5,886247,6E6E6E,6E6E6E,454545,886247"><vp x="3" y="-1" z="5"/></o></c><c><o r="-1,0,0,0,-1,0,0,0,1" bc="454545" ac="454545" sc="6,6E6E6E,454545,6E6E6E,454545,6E6E6E,6E6E6E"><vp x="3" y="-2" z="5"/></o></c><c d="02_wedge"><o r="-1,0,0,0,0,-1,0,-1,0" bc="454545" ac="454545" sc="5,6E6E6E,6E6E6E,6E6E6E,6E6E6E,6E6E6E"><vp x="3" y="-1" z="-10"/></o></c><c d="02_wedge"><o r="-1,0,0,0,0,-1,0,-1,0" bc="454545" ac="454545" sc="5,6E6E6E,7E4422,6E6E6E,6E6E6E,886247"><vp x="-3" y="-1" z="-10"/></o></c><c><o r="-1,0,0,0,-1,0,0,0,1" bc="454545" ac="454545" sc="6,6E6E6E,6E6E6E,6E6E6E,454545,6E6E6E,6E6E6E"><vp x="3" y="-2" z="-10"/></o></c><c><o r="-1,0,0,0,-1,0,0,0,1" bc="454545" ac="454545" sc="6,6E6E6E,6E6E6E,6E6E6E,454545,6E6E6E,7E4422"><vp x="-3" y="-2" z="-10"/></o></c><c d="linear_compact_module"><o r="-1,0,0,0,0,1,0,1,0" bc="6E6E6E" bc2="454545" bc3="454545" ac="454545" sc="5,6E6E6E,454545,454545,454545,454545"><vp z="-2"/></o></c><c d="linear_compact_base"><o r="-1,0,0,0,0,1,0,1,0" bc="454545" ac="454545" sc="5,6E6E6E,454545,454545,454545,454545" gear_ratio="2" input_velocity="1"><vp y="-2" z="-2"/><logic_slots><slot/><slot/><slot/><slot/></logic_slots></o></c><c><o r="1,0,0,0,1,0,0,0,1" bc="6E6E6E" ac="6E6E6E" sc="6"><vp x="3" y="2" z="-3"/></o></c><c><o bc="6E6E6E" ac="6E6E6E" sc="6"><vp x="2" y="2" z="-3"/></o></c><c><o bc="6E6E6E" ac="6E6E6E" sc="6,6E6E6E,7B5236,6E6E6E,6E6E6E,7B5236,6E6E6E"><vp x="-2" y="2" z="-3"/></o></c><c><o bc="6E6E6E" ac="6E6E6E" sc="6"><vp x="-1" y="2" z="-3"/></o></c><c><o bc="6E6E6E" ac="6E6E6E" sc="6"><vp y="2" z="-3"/></o></c><c><o bc="6E6E6E" ac="6E6E6E" sc="6"><vp x="1" y="2" z="-3"/></o></c><c><o r="1,0,0,0,0,-1,0,1,0" bc="6E6E6E" ac="6E6E6E" sc="6"><vp x="3" y="2" z="-4"/></o></c><c><o r="1,0,0,0,0,-1,0,1,0" bc="6E6E6E" ac="6E6E6E" sc="6"><vp x="3" y="2" z="-5"/></o></c><c><o r="1,0,0,0,0,-1,0,1,0" bc="6E6E6E" ac="6E6E6E" sc="6"><vp x="3" y="2" z="-6"/></o></c><c><o r="1,0,0,0,0,-1,0,1,0" bc="6E6E6E" ac="6E6E6E" sc="6,7B5236,6E6E6E,6E6E6E,6E6E6E,7B5236,6E6E6E"><vp x="3" y="2" z="-7"/></o></c><c><o r="1,0,0,0,0,-1,0,1,0" bc="6E6E6E" ac="6E6E6E" sc="6,7B5236,6E6E6E,6E6E6E,6E6E6E,7B5236,7B5236"><vp x="3" y="2" z="-8"/></o></c><c><o r="1,0,0,0,0,-1,0,1,0" bc="6E6E6E" ac="6E6E6E" sc="6,7B5236,6E6E6E,7B5236,6E6E6E,6E6E6E,7B5236"><vp x="3" y="2" z="-9"/></o></c><c><o r="1,0,0,0,0,-1,0,1,0" bc="6E6E6E" ac="6E6E6E" sc="6,7B5236,6E6E6E,6E6E6E,6E6E6E,7B5236,6E6E6E"><vp x="-3" y="2" z="-4"/></o></c><c><o r="1,0,0,0,0,-1,0,1,0" bc="6E6E6E" ac="6E6E6E" sc="6,7B5236,6E6E6E,7B5236,6E6E6E,6E6E6E,6E6E6E"><vp x="2" y="2" z="-9"/></o></c><c><o r="1,0,0,0,0,-1,0,1,0" bc="6E6E6E" ac="6E6E6E" sc="6,7B5236,6E6E6E,6E6E6E,6E6E6E,6E6E6E,6E6E6E"><vp x="-3" y="2" z="-5"/></o></c><c><o r="1,0,0,0,0,-1,0,1,0" bc="6E6E6E" ac="6E6E6E" sc="6"><vp x="1" y="2" z="-9"/></o></c><c><o r="1,0,0,0,0,-1,0,1,0" bc="6E6E6E" ac="6E6E6E" sc="6,7B5236,6E6E6E,6E6E6E,6E6E6E,7B5236,7B5236"><vp x="-3" y="2" z="-6"/></o></c><c><o r="1,0,0,0,0,-1,0,1,0" bc="6E6E6E" ac="6E6E6E" sc="6,7B5236,6E6E6E,7B5236,6E6E6E,7B5236,6E6E6E"><vp y="2" z="-6"/></o></c><c><o r="1,0,0,0,0,-1,0,1,0" bc="6E6E6E" ac="6E6E6E" sc="6,7B5236,6E6E6E,6E6E6E,6E6E6E,6E6E6E,7B5236"><vp x="-3" y="2" z="-7"/></o></c><c><o r="1,0,0,0,0,-1,0,1,0" bc="6E6E6E" ac="6E6E6E" sc="6"><vp x="-1" y="2" z="-9"/></o></c><c><o r="1,0,0,0,0,-1,0,1,0" bc="6E6E6E" ac="6E6E6E" sc="6"><vp x="-3" y="2" z="-8"/></o></c><c><o r="1,0,0,0,0,-1,0,1,0" bc="6E6E6E" ac="6E6E6E" sc="6"><vp x="-2" y="2" z="-9"/></o></c><c><o r="1,0,0,0,0,-1,0,1,0" bc="6E6E6E" ac="6E6E6E" sc="6"><vp x="-3" y="2" z="-9"/></o></c><c d="trans_straight"><o r="0,1,0,0,0,-1,-1,0,0" bc="6E6E6E" ac="6E6E6E" sc="2"><vp x="-3" z="-6"/></o></c><c d="trans_straight"><o r="0,1,0,0,0,-1,-1,0,0" bc="6E6E6E" ac="6E6E6E" sc="2"><vp x="-3" y="1" z="-6"/></o></c><c d="trans_straight"><o r="0,1,0,0,0,-1,-1,0,0" bc="6E6E6E" ac="6E6E6E" sc="2"><vp z="-9"/></o></c><c d="trans_straight"><o r="0,1,0,0,0,-1,-1,0,0" bc="6E6E6E" ac="6E6E6E" sc="2"><vp y="1" z="-9"/></o></c><c><o r="1,0,0,0,1,0,0,0,1" bc="6E6E6E" ac="6E6E6E" sc="6"><vp x="-3" z="-9"/></o></c><c><o r="1,0,0,0,1,0,0,0,1" bc="6E6E6E" ac="6E6E6E" sc="6"><vp x="-3" y="1" z="-9"/></o></c><c><o r="1,0,0,0,1,0,0,0,1" bc="6E6E6E" ac="6E6E6E" sc="6"><vp x="-3" z="-3"/></o></c><c><o r="1,0,0,0,1,0,0,0,1" bc="6E6E6E" ac="6E6E6E" sc="6,7B5236,6E6E6E,6E6E6E,6E6E6E,7B5236,6E6E6E"><vp x="-3" y="1" z="-3"/></o></c><c><o r="1,0,0,0,1,0,0,0,1" bc="6E6E6E" ac="6E6E6E" sc="6"><vp x="3" z="-3"/></o></c><c><o r="1,0,0,0,1,0,0,0,1" bc="6E6E6E" ac="6E6E6E" sc="6"><vp x="3" y="1" z="-3"/></o></c><c><o r="0,0,-1,1,0,0,0,-1,0" bc="454545" ac="454545" sc="6,6E6E6E,6E6E6E,454545,454545,454545,6E6E6E"><vp x="1" y="-1" z="-7"/></o></c><c><o r="1,0,0,0,1,0,0,0,1" bc="6E6E6E" ac="6E6E6E" sc="6"><vp x="3" z="-9"/></o></c><c><o r="1,0,0,0,1,0,0,0,1" bc="6E6E6E" ac="6E6E6E" sc="6,6E6E6E,7B5236,6E6E6E,6E6E6E,6E6E6E,7B5236"><vp x="3" y="1" z="-9"/></o></c><c d="trans_straight"><o r="1,0,0,0,0,-1,0,1,0" bc="7B5236" bc2="6E6E6E" bc3="6E6E6E" ac="6E6E6E" sc="2,6E6E6E,6E6E6E"><vp x="-1" y="2" z="-6"/></o></c><c d="trans_straight"><o r="1,0,0,0,0,-1,0,1,0" bc="7B5236" bc2="6E6E6E" bc3="6E6E6E" ac="6E6E6E" sc="2,6E6E6E,6E6E6E"><vp x="-2" y="2" z="-6"/></o></c><c d="trans_straight"><o r="0,0,1,1,0,0,0,1,0" bc="6E6E6E" ac="6E6E6E" sc="2"><vp y="2" z="-4"/></o></c><c d="trans_straight"><o r="0,0,1,1,0,0,0,1,0" bc="6E6E6E" ac="6E6E6E" sc="2"><vp y="2" z="-5"/></o></c><c d="trans_straight"><o r="0,0,1,1,0,0,0,1,0" bc="7B5236" bc2="6E6E6E" bc3="6E6E6E" ac="6E6E6E" sc="2,6E6E6E,6E6E6E"><vp y="2" z="-7"/></o></c><c d="trans_straight"><o r="0,0,1,1,0,0,0,1,0" bc="6E6E6E" ac="6E6E6E" sc="2"><vp y="2" z="-8"/></o></c><c d="trans_straight"><o r="-1,0,0,0,0,1,0,1,0" bc="6E6E6E" ac="6E6E6E" sc="2"><vp x="1" y="2" z="-6"/></o></c><c d="trans_straight"><o r="-1,0,0,0,0,1,0,1,0" bc="6E6E6E" ac="6E6E6E" sc="2"><vp x="2" y="2" z="-6"/></o></c><c d="button_toggle"><o bc="7B5236" bc2="6E6E6E" bc3="6E6E6E" ac="6E6E6E" sc="5,7B5236,7B5236,6E6E6E,6E6E6E,6E6E6E" custom_name="MISSION_TURNON" hold_duration="1"><vp x="-3" y="2" z="-3"/><logic_slots><slot/><slot/><slot/><slot/><slot/></logic_slots><min_lever_value text="0"/><max_lever_value text="1" value="1"/><starting_lever_value text="0"/></o></c><c d="altimeter"><o r="0,0,-1,-1,0,0,0,1,0" bc="6E6E6E" ac="6E6E6E" sc="5" timer_scalar_1="0.183" timer_scalar_2="0.183"><vp x="1" y="-2" z="-4"/><logic_slots><slot/><slot/><slot/><slot/><slot/><slot/><slot/><slot/><slot/><slot/><slot/><slot><value/></slot><slot><value/></slot><slot><value/></slot></logic_slots><property_output_float_val text="0"/><min_threshold text="0"/><max_threshold text="0"/><pid_controller_ki text="1" value="1"/><pid_controller_kp text="1" value="1"/><pid_controller_kd text="1" value="1"/><pid_controller_max_error text="0"/><exp text="2" value="2"/><min_lever_value text="-1" value="-1"/><max_lever_value text="1" value="1"/><starting_lever_value text="0"/></o></c><c d="dial"><o r="0,1,0,0,0,1,1,0,0" bc="6E6E6E" ac="6E6E6E" sc="5" custom_name="LBJACKLIFTER" decimal_point_pos="3"><vp y="-2" z="-4"/><logic_slots><slot editor_connected="1"/><slot/><slot editor_connected="1"/></logic_slots><min_value text="-1.0" value="-1"/><max_value text="1.0" value="1"/></o></c><c d="microprocessor"><o r="-1,0,0,0,-1,0,0,0,1" bc="6E6E6E" ac="6E6E6E" sc="22"><microprocessor_definition name="Mission_LifterMC" description="No description set." width="3" length="2" id_counter="23" id_counter_node="5" sym0="8196" sym1="16382" sym2="4" sym3="132" sym4="132" sym5="132" sym6="132" sym7="132" sym8="676" sym9="452" sym10="132" sym11="4" sym12="4"><nodes><n id="1" component_id="1"><node label="IsTurnedOn" mode="1" description="The input signal to be processed."/></n><n id="2" component_id="4"><node label="Direction" type="1" description="The input signal to be processed."><position x="1" z="1"/></node></n><n id="3" component_id="6"><node label="AltitudeBase" mode="1" type="1" description="The input signal to be processed."><position z="1"/></node></n><n id="4" component_id="9"><node label="AltitudeMax" type="1" description="The input signal to be processed."><position x="2" z="1"/></node></n><n id="5" component_id="11"><node label="AltitudeCurrent" mode="1" type="1" description="The input signal to be processed."><position x="1"/></node></n></nodes><group><data type="1044640632"><inputs/><outputs/></data><components><c type="58"><object id="17" n="This MC Works Fine" v="No need to edit it"><pos y="1.5"/></object></c><c type="56"><object id="18" script="altMax = 0
ticks = 0
function onTick()
    ticks = ticks + 1

    altBase = input.getNumber(1)
    altCurrent = input.getNumber(2)
    altMax = math.max(altMax, altCurrent - altBase)

    isTurnedOn = input.getBool(1)

    moveDirection = 0
    speed = 1/120 -- up for 4 seconds, down for 4 seconds
    if isTurnedOn then
        moveDirection = math.sin(speed* (ticks-120)) 
    end

    
    output.setNumber(1, -moveDirection) -- invert due to how we built it
    output.setNumber(2, altMax)
end"><pos x="0.25"/><in1 component_id="21"/><in2/><out1/><out2/></object></c><c type="31"><object id="19" i="1"><pos x="1.75" y="-0.25"/><in1 component_id="18"/><out1/></object></c><c type="31"><object id="20"><pos x="1.75" y="0.5"/><in1 component_id="18"/><out1/></object></c><c type="41"><object id="21" count="1"><pos x="-1" y="0.5"/><inc component_id="22"/><in1 component_id="1"/><out1/></object></c><c type="40"><object id="22" count="2"><pos x="-1" y="-0.5"/><inc/><in1 component_id="6"/><in2 component_id="11"/><out1/></object></c></components><components_bridge><c><object id="1"><pos x="-2.5" y="0.5"/><in1/><out1/></object></c><c type="3"><object id="4"><pos x="3" y="0.5"/><in1 component_id="20"/><out1/></object></c><c type="2"><object id="6"><pos x="-2.5" y="-0.25"/><in1/><out1/></object></c><c type="3"><object id="9"><pos x="3" y="-0.25"/><in1 component_id="19"/><out1/></object></c><c type="2"><object id="11"><pos x="-2.5" y="-0.75"/><in1/><out1/></object></c></components_bridge><groups/></group></microprocessor_definition><vp y="-2" z="-7"/><logic_slots><slot/><slot/><slot/><slot/><slot/></logic_slots></o></c><c><o r="1,0,0,0,0,-1,0,1,0" bc="6E6E6E" ac="6E6E6E" sc="6"><vp y="8" z="-3"/></o></c><c><o r="1,0,0,0,0,-1,0,1,0" bc="6E6E6E" ac="6E6E6E" sc="6"><vp x="-1" y="8" z="-3"/></o></c><c><o bc="6E6E6E" ac="6E6E6E" sc="6"><vp x="-2" y="8" z="-3"/></o></c><c><o r="1,0,0,0,1,0,0,0,1" bc="6E6E6E" ac="6E6E6E" sc="6"><vp x="-2" y="3" z="-3"/></o></c><c><o r="1,0,0,0,1,0,0,0,1" bc="6E6E6E" ac="6E6E6E" sc="6"><vp x="-2" y="4" z="-3"/></o></c><c><o r="1,0,0,0,1,0,0,0,1" bc="6E6E6E" ac="6E6E6E" sc="6"><vp x="-2" y="5" z="-3"/></o></c><c><o r="1,0,0,0,1,0,0,0,1" bc="6E6E6E" ac="6E6E6E" sc="6"><vp x="-2" y="6" z="-3"/></o></c><c><o r="1,0,0,0,1,0,0,0,1" bc="6E6E6E" ac="6E6E6E" sc="6"><vp x="-2" y="7" z="-3"/></o></c><c><o r="0,0,-1,1,0,0,0,-1,0" bc="6E6E6E" ac="6E6E6E" sc="6"><vp x="1" y="8" z="-3"/></o></c><c><o r="0,0,-1,1,0,0,0,-1,0" bc="6E6E6E" ac="6E6E6E" sc="6"><vp x="2" y="8" z="-3"/></o></c><c><o r="1,0,0,0,1,0,0,0,1" bc="6E6E6E" ac="6E6E6E" sc="6"><vp x="2" y="3" z="-3"/></o></c><c><o r="1,0,0,0,1,0,0,0,1" bc="6E6E6E" ac="6E6E6E" sc="6"><vp x="2" y="4" z="-3"/></o></c><c><o r="1,0,0,0,1,0,0,0,1" bc="6E6E6E" ac="6E6E6E" sc="6"><vp x="2" y="5" z="-3"/></o></c><c><o r="1,0,0,0,1,0,0,0,1" bc="6E6E6E" ac="6E6E6E" sc="6"><vp x="2" y="6" z="-3"/></o></c><c><o r="1,0,0,0,1,0,0,0,1" bc="6E6E6E" ac="6E6E6E" sc="6"><vp x="2" y="7" z="-3"/></o></c><c d="linear_compact_module"><o r="1,0,0,0,0,1,0,-1,0" bc="6E6E6E" bc2="454545" bc3="454545" ac="454545" sc="5,6E6E6E,454545,454545,454545,454545"><vp y="3" z="-2"/></o></c><c d="linear_compact_module"><o r="0,1,0,0,0,1,1,0,0" bc="6E6E6E" ac="6E6E6E" sc="5"><vp y="2" z="-2"/></o></c><c d="railing_segment_extension_diag"><o r="-1,0,0,0,0,-1,0,-1,0" bc="7A5543" ac="7A5543" sc="14"><vp x="2" y="-1" z="2"/></o></c><c d="railing_segment_extension"><o r="-1,0,0,0,0,-1,0,-1,0" bc="7A5543" ac="7A5543" sc="8"><vp x="-2" y="-1" z="4"/></o></c><c d="railing_segment_end"><o r="0,0,-1,0,1,0,1,0,0" bc="7A5543" ac="7A5543" sc="5"><vp x="-3" z="4"/></o></c><c d="railing_segment_end"><o r="0,0,1,0,1,0,-1,0,0" bc="7A5543" ac="7A5543" sc="5"><vp x="-3" z="-2"/></o></c><c d="railing_segment_end"><o r="0,0,1,0,1,0,-1,0,0" bc="7A5543" ac="7A5543" sc="5"><vp x="3" z="-2"/></o></c><c d="railing_segment_end"><o r="0,0,-1,0,1,0,1,0,0" bc="7A5543" ac="7A5543" sc="5"><vp x="3" z="4"/></o></c><c d="railing_segment_extension"><o r="0,0,1,0,1,0,-1,0,0" bc="7A5543" ac="7A5543" sc="8"><vp x="3" z="3"/></o></c><c d="railing_segment_extension"><o r="0,0,1,0,1,0,-1,0,0" bc="7A5543" ac="7A5543" sc="8"><vp x="3" z="2"/></o></c><c d="railing_segment_extension"><o r="0,0,1,0,1,0,-1,0,0" bc="7A5543" ac="7A5543" sc="8"><vp x="-3" z="-1"/></o></c><c d="railing_extension_angle"><o r="1,0,0,0,1,0,0,0,1" bc="7A5543" ac="7A5543" sc="10"><vp x="-3"/></o></c><c d="railing_extension_angle"><o r="-1,0,0,0,1,0,0,0,-1" bc="7A5543" ac="7A5543" sc="10"><vp x="-3" z="3"/></o></c><c><o bc="6E6E6E" ac="6E6E6E" sc="6"><vp y="2" z="-9"/></o></c><c d="rope_hook"><o r="1,0,0,0,0,-1,0,1,0" bc="6E6E6E" ac="6E6E6E" sc="6" input_velocity="1"><vp y="-1" z="-10"/><logic_slots><slot><value/></slot><slot><value/></slot><slot/><slot/><slot><value/></slot><slot><value/></slot><slot><value/></slot><slot><value/></slot><slot/><slot/><slot/></logic_slots></o></c></components></body><body unique_id="5"><components><c><o r="1,0,0,0,1,0,0,0,1" bc="454545" ac="454545" sc="6,80573F,454545,454545,454545,454545,454545"><vp y="-2"/></o></c><c><o bc="454545" ac="454545" sc="6"><vp x="-1" y="-2"/></o></c><c><o bc="454545" ac="454545" sc="6"><vp x="-2" y="-2"/></o></c><c><o r="1,0,0,0,0,1,0,-1,0" bc="454545" ac="454545" sc="6"><vp x="-2" y="-2" z="1"/></o></c><c><o r="1,0,0,0,0,1,0,-1,0" bc="454545" ac="454545" sc="6,454545,80573F,454545,454545,454545,80573F"><vp x="-2" y="-2" z="2"/></o></c><c><o r="1,0,0,0,0,1,0,-1,0" bc="454545" ac="454545" sc="6,454545,454545,454545,454545,454545,80573F"><vp x="-2" y="-2" z="3"/></o></c><c><o r="1,0,0,0,0,1,0,-1,0" bc="454545" ac="454545" sc="6,454545,80573F,454545,454545,454545,454545"><vp x="-2" y="-2" z="4"/></o></c><c><o r="0,0,-1,1,0,0,0,-1,0" bc="454545" ac="454545" sc="6"><vp x="1" y="-2"/></o></c><c><o r="0,0,-1,1,0,0,0,-1,0" bc="454545" ac="454545" sc="6"><vp x="2" y="-2"/></o></c><c><o r="1,0,0,0,0,1,0,-1,0" bc="454545" ac="454545" sc="6"><vp x="2" y="-2" z="1"/></o></c><c><o r="1,0,0,0,0,1,0,-1,0" bc="454545" ac="454545" sc="6"><vp x="2" y="-2" z="2"/></o></c><c><o r="1,0,0,0,0,1,0,-1,0" bc="454545" ac="454545" sc="6"><vp x="2" y="-2" z="3"/></o></c><c d="08_wedge_4"><o r="-1,0,0,0,1,0,0,0,-1" bc="454545" ac="454545" sc="17,454545,454545,454545,454545,454545,454545,454545,454545,454545,454545,454545,454545,454545,454545,80573F,454545,80573F"><vp x="2" y="-2" z="5"/></o></c><c d="08_wedge_4"><o r="-1,0,0,0,1,0,0,0,-1" bc="454545" ac="454545" sc="17,80573F,454545,454545,7B5236,454545,454545,454545,454545,454545,454545,454545,454545,454545,454545,454545,80573F,454545"><vp x="-2" y="-2" z="5"/></o></c><c d="linear_compact_head"><o r="-1,0,0,0,0,1,0,1,0" bc="454545" ac="454545" sc="5" gear_ratio="2" input_velocity="1"><vp y="-2" z="-1"/><logic_slots><slot/><slot/><slot/><slot/></logic_slots></o></c><c d="altimeter"><o r="1,0,0,0,0,-1,0,1,0" bc="6E6E6E" ac="6E6E6E" sc="5,6E6E6E,7B5236,7B5236,454545,454545" timer_scalar_1="0.183" timer_scalar_2="0.183"><vp x="2" y="-2" z="4"/><logic_slots><slot/><slot/><slot/><slot/><slot/><slot/><slot/><slot/><slot/><slot/><slot/><slot><value/></slot><slot><value/></slot><slot><value/></slot></logic_slots><property_output_float_val text="0"/><min_threshold text="0"/><max_threshold text="0"/><pid_controller_ki text="1" value="1"/><pid_controller_kp text="1" value="1"/><pid_controller_kd text="1" value="1"/><pid_controller_max_error text="0"/><exp text="2" value="2"/><min_lever_value text="-1" value="-1"/><max_lever_value text="1" value="1"/><starting_lever_value text="0"/></o></c><c d="trans_straight"><o r="-1,0,0,0,0,-1,0,-1,0" bc="7A5543" ac="7A5543" sc="2"><vp x="1" y="-2" z="4"/></o></c><c d="trans_straight"><o r="-1,0,0,0,0,-1,0,-1,0" bc="7A5543" ac="7A5543" sc="2"><vp y="-2" z="4"/></o></c><c d="trans_straight"><o r="-1,0,0,0,0,-1,0,-1,0" bc="7A5543" ac="7A5543" sc="2"><vp x="-1" y="-2" z="4"/></o></c><c d="trans_straight"><o r="-1,0,0,0,0,-1,0,-1,0" bc="7A5543" ac="7A5543" sc="2"><vp x="1" y="-2" z="2"/></o></c><c d="trans_straight"><o r="-1,0,0,0,0,-1,0,-1,0" bc="7A5543" ac="7A5543" sc="2"><vp y="-2" z="2"/></o></c><c d="trans_straight"><o r="-1,0,0,0,0,-1,0,-1,0" bc="7A5543" ac="7A5543" sc="2"><vp x="-1" y="-2" z="2"/></o></c></components></body></bodies><logic_node_links><logic_node_link type="1"><voxel_pos_0 x="-2" y="-2" z="-6"/><voxel_pos_1 y="-2" z="-4"/></logic_node_link><logic_node_link type="4"><voxel_pos_0 y="-2" z="-4"/><voxel_pos_1 x="2" y="1" z="-5"/></logic_node_link><logic_node_link type="4"><voxel_pos_0 x="-3" y="2" z="-3"/><voxel_pos_1 x="2" y="1" z="-5"/></logic_node_link><logic_node_link><voxel_pos_0 x="-3" y="2" z="-3"/><voxel_pos_1 y="-2" z="-3"/></logic_node_link><logic_node_link><voxel_pos_0 x="-3" y="2" z="-3"/><voxel_pos_1 y="-2" z="-7"/></logic_node_link><logic_node_link type="1"><voxel_pos_0 x="1" y="-2" z="-4"/><voxel_pos_1 y="-2" z="-6"/></logic_node_link><logic_node_link type="1"><voxel_pos_0 x="2" y="-2" z="4"/><voxel_pos_1 x="-1" y="-2" z="-7"/></logic_node_link><logic_node_link type="1"><voxel_pos_0 x="-1" y="-2" z="-6"/><voxel_pos_1 y="-2" z="-2"/></logic_node_link></logic_node_links></vehicle>